<?xml version='1.0' encoding='windows-1252'?>
<song xmlns="http://openlyrics.info/namespace/2009/song" version="0.8" createdIn="OpenLP 2.0.5" createdBy="Projeto HASDLP - https://github.com/jesobreira/hasdlp" modifiedIn="OpenLP 2.0.5" modifiedDate="2015-04-24T02:42:01">
  <properties>
    <titles>
      <title>174 - Segue-Me</title>
    </titles>
    <authors>
      <author>HASD</author>
    </authors>
  </properties>
  <lyrics>
    <verse name="v1a">
      <lines><![CDATA[
		Segue-Me
	  ]]></lines>
    </verse>
<verse name="v1b">
      <lines><![CDATA[
		1. Escuta a voz do meu Jesus:
   Segue-Me, segue-Me, segue-Me.
   Guiar-te-ei à eterna luz;
   Segue-Me, segue-Me, segue-Me.
   Por ti Eu toda a lei cumpri;
   Por ti o amargo fel bebi;
   Por ti a morte já sofri;
   Segue-Me, segue-Me, segue-Me.
	  ]]></lines>
    </verse>
<verse name="v1c">
      <lines><![CDATA[
		2. Liberto dos pecados teus,
   Segue-Me, segue-Me, segue-Me.
   Guiar-te-ei aos altos Céus;
   Segue-Me, segue-Me, segue-Me.
   Oh, quantas vezes te chamei,
   E tu quebraste a Minha lei;
   Mas fiador teu Eu fiquei;
   Segue-Me, segue-Me, segue-Me.
	  ]]></lines>
    </verse>
<verse name="v1d">
      <lines><![CDATA[
		3. Em Mim tu podes descansar;
   Segue-Me, segue-Me, segue-Me.
   Vem teus cuidados Me entregar;
   Segue-Me, segue-Me, segue-Me.
   Eu sou teu Deus, teu Salvador;
   Eu te amo muito, ó pecador;
   Ó, deixa todo o teu temor;
   Segue-Me, segue-Me, segue-Me.
	  ]]></lines>
    </verse>

  </lyrics>
</song>
