<?xml version='1.0' encoding='windows-1252'?>
<song xmlns="http://openlyrics.info/namespace/2009/song" version="0.8" createdIn="OpenLP 2.0.5" createdBy="Projeto HASDLP - https://github.com/jesobreira/hasdlp" modifiedIn="OpenLP 2.0.5" modifiedDate="2015-04-24T02:42:01">
  <properties>
    <titles>
      <title>412 - Comunhão Preciosa</title>
    </titles>
    <authors>
      <author>HASD</author>
    </authors>
  </properties>
  <lyrics>
    <verse name="v1a">
      <lines><![CDATA[
		Comunhão Preciosa
	  ]]></lines>
    </verse>
<verse name="v1b">
      <lines><![CDATA[
		1. Quão preciosas são as horas 
   Na presença de Jesus!
   Comunhão deliciosa,
   De minh'alma com a luz!
   Os cuidados deste mundo
   Não me podem abalar,
   Pois é Ele o meu abrigo
   Quando o tentador chegar,
   Quando o tentador chegar.
	  ]]></lines>
    </verse>
<verse name="v1c">
      <lines><![CDATA[
		2. Ao sentir-me rodeado
   De cuidados terreais,
   Conturbado ou abatido,
   Ou em dúvidas fatais,
   A Jesus eu me dirijo
   Nestes tempos de aflição;
   As palavras que Ele fala
   Trazem paz ao coração,
   Trazem paz ao coração.
	  ]]></lines>
    </verse>
<verse name="v1d">
      <lines><![CDATA[
		3. Se Lhe conto meus temores, 
   Toda a minha imperfeição,
   Ele escuta com paciência 
   Essa triste confissão;
   Com ternura repreende 
   Meu pecado e todo o mal.
   É Jesus o meu amigo,
   O melhor e mais leal,
   O melhor e mais leal.
	  ]]></lines>
    </verse>
<verse name="v1e">
      <lines><![CDATA[
		4. Se quereis saber quão doce
   É a secreta comunhão,
   Podereis mui bem prová-la,
   Fruireis consolação;
   Procurai estar sozinhos,
   Em conversa com Jesus:
   Provareis na vossa vida 
   Sua graça e Sua luz,
   Sua graça e Sua luz.
	  ]]></lines>
    </verse>

  </lyrics>
</song>
