<?xml version='1.0' encoding='windows-1252'?>
<song xmlns="http://openlyrics.info/namespace/2009/song" version="0.8" createdIn="OpenLP 2.0.5" createdBy="Projeto HASDLP - https://github.com/jesobreira/hasdlp" modifiedIn="OpenLP 2.0.5" modifiedDate="2015-04-24T02:42:01">
  <properties>
    <titles>
      <title>514 - O Alvo Supremo</title>
    </titles>
    <authors>
      <author>HASD</author>
    </authors>
  </properties>
  <lyrics>
    <verse name="v1a">
      <lines><![CDATA[
		O Alvo Supremo
	  ]]></lines>
    </verse>
<verse name="v1b">
      <lines><![CDATA[
		1. O mundo vil já desprezei
   E seu prazer abominei;
   E rogo a Ti, ó Salvador,
   Que agora eu viva em Teu amor.
	  ]]></lines>
    </verse>
<verse name="v1c">
      <lines><![CDATA[
		CORO: Ó meu Jesus, me guia, sim,
      Com Tua luz e amor sem fim, 
      E me sustém até chegar 
      Às portas do celeste lar.
	  ]]></lines>
    </verse>
<verse name="v1d">
      <lines><![CDATA[
		2. No mundo aqui não tenho paz, 
   Pois ele não me satisfaz;
   Mas com Jesus eu hei de ter 
   Grande alegria em meu viver.
	  ]]></lines>
    </verse>
<verse name="v1e">
      <lines><![CDATA[
		3. De meu Senhor eu quero ser, 
   E Sua causa promover.
   E pela fé já avistei
   O lar em que descansarei.
	  ]]></lines>
    </verse>

  </lyrics>
</song>
