<?xml version='1.0' encoding='windows-1252'?>
<song xmlns="http://openlyrics.info/namespace/2009/song" version="0.8" createdIn="OpenLP 2.0.5" createdBy="Projeto HASDLP - https://github.com/jesobreira/hasdlp" modifiedIn="OpenLP 2.0.5" modifiedDate="2015-04-24T02:42:01">
  <properties>
    <titles>
      <title>576 - Pai, Sê Presente</title>
    </titles>
    <authors>
      <author>HASD</author>
    </authors>
  </properties>
  <lyrics>
    <verse name="v1a">
      <lines><![CDATA[
		Pai, Sê Presente
	  ]]></lines>
    </verse>
<verse name="v1b">
      <lines><![CDATA[
		Pai, sê presente neste templo;
Faz-nos ouvir a Tua voz;
Brilhe em Jesus o nosso exemplo,
E Habita em nós.
	  ]]></lines>
    </verse>

  </lyrics>
</song>
