<?xml version="1.0" encoding="utf-8"?>
<song xmlns="http://openlyrics.info/namespace/2009/song" version="0.8" createdIn="OpenLP 2.0.5" createdBy="Projeto HASDLP - https://github.com/jesobreira/hasdlp" modifiedIn="OpenLP 2.0.5" modifiedDate="2022-08-02T01:41:01"><properties><titles><title>463 - Espero a Manhã Radiosa</title></titles>		<authors><author>James Henry Fillmore</author><author>Sr</author></authors></properties>	  <lyrics><verse name="v1"><lines><![CDATA[
Espero a manhã radiosa,
O bendito alvorecer,
Quando as mágoas e tristezas
Desta vida eu esquecer
]]></lines></verse><verse name="v2"><lines><![CDATA[
Coro:
Eu espero mui ansioso,
Meu Jesus aqui voltar;
Eu aguardo as boas-vindas
De Jesus, na praia de outro mar.
]]></lines></verse><verse name="v3"><lines><![CDATA[
Espero já mui cansado
Dos embates do viver,
Mas quando isto for passado,
Galardão hei de receber.
]]></lines></verse><verse name="v4"><lines><![CDATA[
Espero já mui ansioso
O celeste lar de amor;
Qual um viajor saudoso,
Quero a vinda do senhor.
]]></lines></verse><verse name="v5"><lines><![CDATA[
Espero encontrar queridos
Na mansão celestial;
Receber do mestre amado.
Um abraço fraternal.
]]></lines></verse></lyrics></song>